{
 "aggregate_function_based_on": "",
 "creation": "2025-09-25 10:31:50.029547",
 "currency": "",
 "docstatus": 0,
 "doctype": "Number Card",
 "document_type": "DAPR Officers",
 "dynamic_filters_json": "[]",
 "filters_json": "[[\"DAPR Officers\",\"p_no\",\"like\",\"%F%\",false]]",
 "function": "Count",
 "idx": 0,
 "is_public": 1,
 "is_standard": 1,
 "label": "Female Officers",
 "modified": "2025-09-25 10:31:50.029547",
 "modified_by": "Administrator",
 "module": "Personnel Management",
 "name": "Female Officers",
 "owner": "Administrator",
 "parent_document_type": "",
 "report_function": "Sum",
 "show_percentage_stats": 1,
 "stats_time_interval": "Daily",
 "type": "Document Type"
}